ChangeLog
LICENSE.MIT
MANIFEST.in
README.rst
pyproject.toml
requirements.txt
setup.cfg
setup.py
tox.ini
examples/ctx.yml
examples/jinja2-incl.j2
examples/jinja2.j2
pkg/copr-build.sh
pkg/package.spec.in
src/anytemplate/__init__.py
src/anytemplate/api.py
src/anytemplate/cli.py
src/anytemplate/compat.py
src/anytemplate/datatypes.py
src/anytemplate/engine.py
src/anytemplate/globals.py
src/anytemplate/utils.py
src/anytemplate.egg-info/PKG-INFO
src/anytemplate.egg-info/SOURCES.txt
src/anytemplate.egg-info/dependency_links.txt
src/anytemplate.egg-info/entry_points.txt
src/anytemplate.egg-info/requires.txt
src/anytemplate.egg-info/top_level.txt
src/anytemplate/engines/__init__.py
src/anytemplate/engines/base.py
src/anytemplate/engines/cheetah.py
src/anytemplate/engines/jinja2.py
src/anytemplate/engines/mako.py
src/anytemplate/engines/pystache.py
src/anytemplate/engines/strtemplate.py
tests/__init__.py
tests/releng.bats
tests/requirements.txt
tests/test_api.py
tests/test_cli.py
tests/test_compat.py
tests/test_engine.py
tests/test_import_errors.py
tests/test_utils.py
tests/engines/__init__.py
tests/engines/test_base.py
tests/engines/test_cheetah.py
tests/engines/test_jinja2.py
tests/engines/test_mako.py
tests/engines/test_pystache.py
tests/engines/test_strtemplate.py
tests/requirements.d/build.txt
tests/requirements.d/engines.txt
tests/requirements.d/lint.txt
tests/requirements.d/rpm.txt
tests/requirements.d/test.txt
tests/requirements.d/type-check.txt