Metadata-Version: 2.1
Name: anytemplate
Version: 0.1.8
Summary: Library to abstract template engines and provide common APIs
Author-email: Satoru SATOH <satoru.satoh@gmail.com>
Maintainer-email: Satoru SATOH <satoru.satoh@gmail.com>
License: MIT
Project-URL: Homepage, https://github.com/ssato/python-anytemplate
Project-URL: Repository, https://github.com/ssato/python-anytemplate
Project-URL: Issues, https://github.com/ssato/python-anytemplate/issues
Project-URL: Changelog, https://github.com/ssato/python-anytemplate/blob/next/ChangeLog
Project-URL: Download, https://pypi.python.org/pypi/anytemplate
Project-URL: Download RPMs, https://copr.fedoraproject.org/coprs/ssato/python-anyconfig/
Project-URL: CI, https://github.com/ssato/python-anytemplate/actions
Classifier: Development Status :: 4 - Beta
Classifier: Intended Audience :: Developers
Classifier: Programming Language :: Python
Classifier: Programming Language :: Python :: 3
Classifier: Programming Language :: Python :: 3.9
Classifier: Programming Language :: Python :: 3.10
Classifier: Programming Language :: Python :: 3.11
Classifier: Programming Language :: Python :: 3.12
Classifier: Environment :: Console
Classifier: Operating System :: OS Independent
Classifier: Topic :: Software Development :: Libraries :: Python Modules
Classifier: Topic :: Text Processing :: Markup
Classifier: Topic :: Utilities
Classifier: License :: OSI Approved :: MIT License
Requires-Python: >=3.9
License-File: LICENSE.MIT
Requires-Dist: anyconfig
Requires-Dist: jinja2
Provides-Extra: engines
Requires-Dist: Cheetah3; extra == "engines"
Requires-Dist: mako; extra == "engines"
Requires-Dist: pystache; extra == "engines"
